[
    {"ticker": "VSMO", "name": "ВСМПО-АВИСМА", "figi": "BBG004S68CV8"},
    {"ticker": "UNAC", "name": "Объединенная авиастроительная корпорация", "figi": "BBG000Q7ZZY2"},
    {"ticker": "CNRU", "name": "Циан", "figi": "TCS00A10ANA1"},
    {"ticker": "VKCO", "name": "ВК", "figi": "TCS00A106YF0"},
    {"ticker": "MGNT", "name": "Магнит", "figi": "BBG004RVFCY3"},
    {"ticker": "KZOSP", "name": "Казаньоргсинтез - акции привилегированные", "figi": "BBG0029SG1C1"},
    {"ticker": "WUSH", "name": "Whoosh", "figi": "TCS00A105EX7"},
    {"ticker": "UGLD", "name": "Южуралзолото ГК", "figi": "TCS00A0JPP37"},
    {"ticker": "LNZL", "name": "Лензолото", "figi": "BBG000SK7JS5"},
    {"ticker": "SELG", "name": "Селигдар", "figi": "BBG002458LF8"},
    {"ticker": "PRFN", "name": "ЧЗПСН-Профнастил", "figi": "TCS00A0JNXF9"},
    {"ticker": "CARM", "name": "КарМани", "figi": "TCS00A105NV2"},
    {"ticker": "RUAL", "name": "РУСАЛ", "figi": "BBG008F2T3T2"},
    {"ticker": "NKHP", "name": "НКХП", "figi": "BBG00BGKYH17"},
    {"ticker": "ALRS", "name": "АЛРОСА", "figi": "BBG004S68B31"},
    {"ticker": "DIAS", "name": "Диасофт", "figi": "TCS00A107ER5"},
    {"ticker": "TATN", "name": "Татнефть", "figi": "BBG004RVFFC0"},
    {"ticker": "RTKM", "name": "Ростелеком", "figi": "BBG004S682Z6"},
    {"ticker": "PRMD", "name": "Промомед", "figi": "TCS30A108JF7"},
    {"ticker": "TGKN", "name": "ТГК-14", "figi": "BBG000RG4ZQ4"},
    {"ticker": "TRNFP", "name": "Транснефть - привилегированные акции", "figi": "BBG00475KHX6"},
    {"ticker": "RAGR", "name": "РусАгро", "figi": "TCS90A0JQUZ6"},
    {"ticker": "GCHE", "name": "Группа Черкизово", "figi": "BBG000RTHVK7"},
    {"ticker": "UWGN", "name": "ОВК", "figi": "TCS90A0JVBT9"},
    {"ticker": "SNGSP", "name": "Сургутнефтегаз - привилегированные акции", "figi": "BBG004S681M2"},
    {"ticker": "FIXR", "name": "Фикс Прайс", "figi": "TCS40A10B5G8"},
    {"ticker": "NKNC", "name": "Нижнекамскнефтехим", "figi": "BBG000GQSRR5"},
    {"ticker": "VRSB", "name": "ТНС энерго Воронеж", "figi": "BBG000BX7DH0"},
    {"ticker": "MBNK", "name": "МТС-Банк", "figi": "TCS00A0JRH43"},
    {"ticker": "MOEX", "name": "Московская Биржа", "figi": "BBG004730JJ5"},
    {"ticker": "KAZTP", "name": "КуйбышевАзот - Акции привилегированные", "figi": "BBG002B9T6Y1"},
    {"ticker": "SNGS", "name": "Сургутнефтегаз", "figi": "BBG0047315D0"},
    {"ticker": "TGKBP", "name": "ТГК-2 - акции привилегированные", "figi": "BBG000Q7GJ60"},
    {"ticker": "PIKK", "name": "ПИК", "figi": "BBG004S68BH6"},
    {"ticker": "ROSN", "name": "Роснефть", "figi": "BBG004731354"},
    {"ticker": "EUTR", "name": "ЕвроТранс", "figi": "TCS00A1002V2"},
    {"ticker": "MRKU", "name": "Россети Урал", "figi": "BBG000VKG4R5"},
    {"ticker": "ENPG", "name": "Эн+", "figi": "BBG000RMWQD4"},
    {"ticker": "T", "name": "Т-Технологии", "figi": "TCS80A107UL4"},
    {"ticker": "MRKV", "name": "Россети Волга", "figi": "BBG000PKWCQ7"},
    {"ticker": "CNTL", "name": "Центральный Телеграф", "figi": "BBG000BBV4M5"},
    {"ticker": "VSEH", "name": "ВИ.РУ", "figi": "TCS10A108K09"},
    {"ticker": "SVAV", "name": "СОЛЛЕРС", "figi": "BBG004S68JR8"},
    {"ticker": "KMAZ", "name": "КАМАЗ", "figi": "BBG000LNHHJ9"},
    {"ticker": "KZOS", "name": "Казаньоргсинтез - акции обыкновенные", "figi": "BBG0029SFXB3"},
    {"ticker": "ELFV", "name": "ЭЛ5-Энерго", "figi": "BBG000F6YPH8"},
    {"ticker": "HEAD", "name": "Хэдхантер", "figi": "TCS20A107662"},
    {"ticker": "ETLN", "name": "МКПАО Эталон Груп", "figi": "TCS50A10C1L6"},
    {"ticker": "SMLT", "name": "ГК Самолет", "figi": "BBG00F6NKQX3"},
    {"ticker": "SBER", "name": "Сбер Банк", "figi": "BBG004730N88"},
    {"ticker": "GECO", "name": "Генетико", "figi": "TCS00A105BN4"},
    {"ticker": "GAZP", "name": "Газпром", "figi": "BBG004730RP0"},
    {"ticker": "BSPB", "name": "Банк Санкт-Петербург", "figi": "BBG000QJW156"},
    {"ticker": "LSNG", "name": "Россети Ленэнерго", "figi": "BBG000NLC9Z6"},
    {"ticker": "RENI", "name": "Ренессанс Страхование", "figi": "BBG00QKJSX05"},
    {"ticker": "POSI", "name": "Группа Позитив", "figi": "TCS00A103X66"},
    {"ticker": "KROT", "name": "Красный Октябрь", "figi": "BBG000NLB2G3"},
    {"ticker": "SIBN", "name": "Газпром нефть", "figi": "BBG004S684M6"},
    {"ticker": "KLSB", "name": "Калужская сбытовая компания", "figi": "BBG000DBD6F6"},
    {"ticker": "CHMK", "name": "ЧМК", "figi": "BBG000RP8V70"},
    {"ticker": "MRKZ", "name": "Россети Северо-Запад", "figi": "BBG000TJ6F42"},
    {"ticker": "APTK", "name": "Аптечная сеть 36,6", "figi": "BBG000K3STR7"},
    {"ticker": "HYDR", "name": "РусГидро", "figi": "BBG00475K2X9"},
    {"ticker": "LNZLP", "name": "Лензолото - привилегированные акции", "figi": "BBG000SR0YS4"},
    {"ticker": "SFIN", "name": "ЭсЭфАй", "figi": "BBG003LYCMB1"},
    {"ticker": "RASP", "name": "Распадская", "figi": "BBG004S68696"},
    {"ticker": "GMKN", "name": "Норильский никель", "figi": "BBG004731489"},
    {"ticker": "UPRO", "name": "Юнипро", "figi": "BBG004S686W0"},
    {"ticker": "MSNG", "name": "Мосэнерго", "figi": "BBG004S687W8"},
    {"ticker": "AFKS", "name": "АФК Система", "figi": "BBG004S68614"},
    {"ticker": "PLZL", "name": "Полюс", "figi": "BBG000R607Y3"},
    {"ticker": "LEAS", "name": "Европлан", "figi": "TCS00A0ZZFS9"},
    {"ticker": "CNTLP", "name": "Центральный Телеграф - акции привилегированные", "figi": "BBG0027F0Y27"},
    {"ticker": "LIFE", "name": "Фармсинтез", "figi": "TCS10A0JR514"},
    {"ticker": "DATA", "name": "Группа Аренадата", "figi": "TCS00A108ZR8"},
    {"ticker": "IRKT", "name": "Яковлев", "figi": "BBG000FWGSZ5"},
    {"ticker": "TTLK", "name": "Таттелеком", "figi": "BBG000RJL816"},
    {"ticker": "SVCB", "name": "Совкомбанк", "figi": "TCS00A0ZZAC4"},
    {"ticker": "GEMC", "name": "United medical group", "figi": "TCS00A107JE2"},
    {"ticker": "PHOR", "name": "ФосАгро", "figi": "BBG004S689R0"},
    {"ticker": "HNFG", "name": "HENDERSON", "figi": "TCS00A106XF2"},
    {"ticker": "TATNP", "name": "Татнефть - привилегированные акции", "figi": "BBG004S68829"},
    {"ticker": "MAGN", "name": "Магнитогорский металлургический комбинат", "figi": "BBG004S68507"},
    {"ticker": "VTBR", "name": "Банк ВТБ", "figi": "BBG004730ZJ9"},
    {"ticker": "BANEP", "name": "Башнефть - привилегированные акции", "figi": "BBG004S686N0"},
    {"ticker": "OKEY", "name": "O'Key Group SA", "figi": "BBG00172J7S9"},
    {"ticker": "MRKP", "name": "Россети Центр и Приволжье", "figi": "BBG000VG1034"},
    {"ticker": "FLOT", "name": "Совкомфлот", "figi": "BBG000R04X57"},
    {"ticker": "ABIO", "name": "Артген", "figi": "TCS10A0JNAB6"},
    {"ticker": "DVEC", "name": "ДЭК", "figi": "BBG000V07CB8"},
    {"ticker": "ZAYM", "name": "МФК Займер", "figi": "TCS00A107RM8"},
    {"ticker": "MTSS", "name": "МТС", "figi": "BBG004S681W1"},
    {"ticker": "OZPH", "name": "Озон Фармацевтика", "figi": "TCS00A109B25"},
    {"ticker": "FEES", "name": "ФСК Россети", "figi": "BBG00475JZZ6"},
    {"ticker": "PMSB", "name": "Пермэнергосбыт", "figi": "BBG000MZL0Y6"},
    {"ticker": "RBCM", "name": "РБК", "figi": "TCS10A0JR6A6"},
    {"ticker": "MSRS", "name": "Россети Московский регион", "figi": "BBG004S687G6"},
    {"ticker": "IRAO", "name": "Интер РАО ЕЭС", "figi": "BBG004S68473"},
    {"ticker": "NSVZ", "name": "Наука-Связь", "figi": "BBG002BCQK67"},
    {"ticker": "BLNG", "name": "Белон", "figi": "TCS20A0J2QG8"},
    {"ticker": "X5", "name": "Корпоративный Центр Икс 5", "figi": "TCS03A108X38"},
    {"ticker": "NVTK", "name": "НОВАТЭК", "figi": "BBG00475KKY8"},
    {"ticker": "UNKL", "name": "ЮУНК", "figi": "BBG002YFXL29"},
    {"ticker": "AQUA", "name": "ИНАРКТИКА", "figi": "BBG000W325F7"},
    {"ticker": "ROLO", "name": "Русолово", "figi": "BBG004Z2RGW8"},
    {"ticker": "OGKB", "name": "Вторая генерирующая компания оптового рынка электроэнергии", "figi": "BBG000RK52V1"},
    {"ticker": "CBOM", "name": "МКБ", "figi": "BBG009GSYN76"},
    {"ticker": "ABRD", "name": "АбрауДюрсо", "figi": "BBG002W2FT69"},
    {"ticker": "TRMK", "name": "Трубная Металлургическая Компания", "figi": "BBG004TC84Z8"},
    {"ticker": "SOFL", "name": "Софтлайн", "figi": "TCS00A0ZZBC2"},
    {"ticker": "KRKNP", "name": "Саратовский НПЗ - акции привилегированные", "figi": "BBG002B2J5X0"},
    {"ticker": "CHMF", "name": "Северсталь", "figi": "BBG00475K6C3"},
    {"ticker": "NKNCP", "name": "Нижнекамскнефтехим (привилегированные)", "figi": "BBG000GQSVC2"},
    {"ticker": "LSRG", "name": "Группа ЛСР", "figi": "BBG004S68C39"},
    {"ticker": "RTKMP", "name": "Ростелеком - Привилегированные акции", "figi": "BBG004S685M3"},
    {"ticker": "MGTSP", "name": "МГТС - акции привилегированные", "figi": "BBG000PZ0833"},
    {"ticker": "KLVZ", "name": "Кристалл", "figi": "TCS00A107KX0"},
    {"ticker": "VEON-RX", "name": "VEON", "figi": "BBG00R4Z2NT4"},
    {"ticker": "YDEX", "name": "Яндекс", "figi": "TCS00A107T19"},
    {"ticker": "BANE", "name": "Башнефть", "figi": "BBG004S68758"},
    {"ticker": "AFLT", "name": "Аэрофлот", "figi": "BBG004S683W7"},
    {"ticker": "MVID", "name": "М.Видео", "figi": "BBG004S68CP5"},
    {"ticker": "PMSBP", "name": "Пермэнергосбыт - акции привилегированные", "figi": "BBG000MZL2S9"},
    {"ticker": "MSTT", "name": "Мостотрест", "figi": "BBG004S68DD6"},
    {"ticker": "MTLR", "name": "Мечел", "figi": "BBG004S68598"},
    {"ticker": "IVAT", "name": "IVA Technologies", "figi": "TCS00A108GD8"},
    {"ticker": "AKRN", "name": "Акрон", "figi": "BBG004S688G4"},
    {"ticker": "MDMG", "name": "Мать и дитя", "figi": "TCS00Y3XYV94"},
    {"ticker": "SBERP", "name": "Сбер Банк - привилегированные акции", "figi": "BBG0047315Y7"},
    {"ticker": "LENT", "name": "Лента", "figi": "BBG0063FKTD9"},
    {"ticker": "ASTR", "name": "Группа Астра", "figi": "RU000A106T36"},
    {"ticker": "RKKE", "name": "РКК Энергия им.С.П.Королева", "figi": "BBG000LWNRP3"},
    {"ticker": "MRKC", "name": "Россети Центр", "figi": "BBG000VH7TZ8"},
    {"ticker": "KAZT", "name": "КуйбышевАзот", "figi": "BBG002B9MYC1"},
    {"ticker": "YAKG", "name": "ЯТЭК", "figi": "BBG002B298N6"},
    {"ticker": "TGKB", "name": "ТГК-2", "figi": "BBG000Q7GG57"},
    {"ticker": "RNFT", "name": "РуссНефть", "figi": "BBG00F9XX7H4"},
    {"ticker": "GTRK", "name": "ГТМ", "figi": "TCS03A0ZYD22"},
    {"ticker": "NLMK", "name": "НЛМК", "figi": "BBG004S681B4"},
    {"ticker": "BELU", "name": "Novabev Group", "figi": "BBG000TY1CD1"},
    {"ticker": "FESH", "name": "ДВМП", "figi": "BBG000QF1Q17"},
    {"ticker": "SGZH", "name": "Сегежа", "figi": "BBG0100R9963"},
    {"ticker": "LSNGP", "name": "Россети Ленэнерго - акции привилегированные", "figi": "BBG000NLCCM3"},
    {"ticker": "MRKS", "name": "Россети Сибирь", "figi": "BBG000VJMH65"},
    {"ticker": "LKOH", "name": "ЛУКОЙЛ", "figi": "BBG004731032"},
    {"ticker": "DELI", "name": "Делимобиль", "figi": "TCS00A107J11"},
    {"ticker": "MGKL", "name": "МГКЛ", "figi": "TCS00A0JVJQ8"},
    {"ticker": "NMTP", "name": "НМТП", "figi": "BBG004S68BR5"},
    {"ticker": "TGKA", "name": "ТГК-1", "figi": "BBG000QFH687"},
    {"ticker": "MTLRP", "name": "Мечел - Привилегированные акции", "figi": "BBG004S68FR6"},
    {"ticker": "MRKY", "name": "Россети Юг", "figi": "BBG000C7P5M7"}
]